columbia_common/__init__.py
columbia_common/schemas/__init__.py
columbia_common/schemas/api_v1/__init__.py
columbia_common/schemas/api_v1/common_crawl.py
columbia_common/schemas/api_v1/mixins/__init__.py
columbia_common/schemas/api_v1/mixins/common_crawl.py
quaerere_columbia_common-0.1.0.dist-info/LICENSE.txt
quaerere_columbia_common-0.1.0.dist-info/METADATA
quaerere_columbia_common-0.1.0.dist-info/WHEEL
quaerere_columbia_common-0.1.0.dist-info/entry_points.txt
quaerere_columbia_common-0.1.0.dist-info/top_level.txt
quaerere_columbia_common-0.1.0.dist-info/RECORD
