Metadata-Version: 2.1
Name: quaerere-columbia-common
Version: 0.1.0
Summary: Common library for columbia and columbia-client
Home-page: https://github.com/QuaererePlatform/columbia-common
Author: Caitlyn O'Hanna
Author-email: ravenoak@virtualxistenz.com
License: AGPLv3+
Project-URL: Documentation, http://quaerere-columbia-common.readthedocs.io/
Project-URL: Source Code, https://github.com/QuaererePlatform/columbia-common
Platform: UNKNOWN
Classifier: Development Status :: 2 - Pre-Alpha
Classifier: License :: OSI Approved :: GNU Affero General Public License v3 or later (AGPLv3+)
Classifier: Operating System :: OS Independent
Classifier: Programming Language :: Python :: 3 :: Only
Classifier: Programming Language :: Python :: 3.6
Classifier: Programming Language :: Python :: 3.7
Requires-Python: >= 3.6
Requires-Dist: marshmallow (<3,>=2.19.0)
Requires-Dist: quaerere-base-common
